nginxlib/__init__.py
nginxlib/exceptions.py
nginxlib/graph.py
nginxlib/main.py
nginxlib/nginxlib.py
nginxlib-0.1.0a0.dist-info/AUTHORS.rst
nginxlib-0.1.0a0.dist-info/LICENSE
nginxlib-0.1.0a0.dist-info/METADATA
nginxlib-0.1.0a0.dist-info/WHEEL
nginxlib-0.1.0a0.dist-info/top_level.txt
nginxlib-0.1.0a0.dist-info/RECORD
