Metadata-Version: 2.1
Name: nginxlib
Version: 0.1.0a0
Summary: Parse nginx logs.
Home-page: https://github.com/briandant/nginxlib
Author: Brian Dant
Author-email: brian.dant@protonmail.com
License: MIT license
Keywords: nginxlib
Platform: UNKNOWN
Classifier: Development Status :: 2 - Pre-Alpha
Classifier: Intended Audience :: Developers
Classifier: License :: OSI Approved :: MIT License
Classifier: Natural Language :: English
Classifier: Programming Language :: Python :: 2
Classifier: Programming Language :: Python :: 2.7
Classifier: Programming Language :: Python :: 3
Classifier: Programming Language :: Python :: 3.4
Classifier: Programming Language :: Python :: 3.5
Classifier: Programming Language :: Python :: 3.6
Classifier: Programming Language :: Python :: 3.7
